BAScraper/BAScraper_async.py
BAScraper/__init__.py
BAScraper/services.py
BAScraper/utils.py
bascraper-0.2.0.dist-info/LICENSE
bascraper-0.2.0.dist-info/METADATA
bascraper-0.2.0.dist-info/WHEEL
bascraper-0.2.0.dist-info/top_level.txt
bascraper-0.2.0.dist-info/RECORD
